{
  "shared_users": [
    {
      "user_id": "1043370582408888",
      "cust_id": "cus_9u41xYrUAcimAH",
      "first_name": "Bharath",
      "last_name": "Reddy",
      "profile_pic": "https://fb-s-c-a.akamaihd.net/h-ak-xfp1/v/t1.0-1/12745644_10153559412743198_3452017161499246690_n.jpg?oh=c5fd4a3e6f81e26cd6313bd11c591aa9&oe=5953EF23&__gda__=1502900904_c27bcae2ed5890a072daccb11f4880f5",
      "locale": "en_US",
      "timezone": -7,
      "gender": "male",
      "createdAt": "2017-04-17T00:50:45.000Z",
      "updatedAt": "2017-08-09T01:29:41.000Z",
      "email": "bharath2890@gmail.com"
    }
  ],
  "payment_details": [
    {
      "id": 3,
      "order_id": 30,
      "user": "1057808377646370",
      "user_bill": 7.99,
      "person_paying": "1057808377646370",
      "selection": "default",
      "confirmed": true,
      "charge": null,
      "createdAt": "2017-07-16T08:54:08.000Z",
      "updatedAt": "2017-08-09T01:29:41.000Z"
    },
    {
      "id": 4,
      "order_id": 30,
      "user": "1043370582408888",
      "user_bill": 15.98,
      "person_paying": "1057808377646370",
      "selection": "updated",
      "confirmed": true,
      "charge": null,
      "createdAt": "2017-07-16T21:23:45.000Z",
      "updatedAt": "2017-08-09T01:29:41.000Z"
    }
  ],
  "user": {
    "user_id": "1057808377646370",
    "cust_id": "cus_AiFtYzNtuoUDh9",
    "first_name": "Meghana",
    "last_name": "Kothaluri",
    "profile_pic": null,
    "locale": null,
    "timezone": null,
    "gender": "female",
    "createdAt": null,
    "updatedAt": "2017-08-09T01:29:41.000Z",
    "email": "skyspywar@yahoo.com"
  },
  "order_id": 30,
  "order_status": "submitted",
  "order_type": "togo",
  "order_bill": 23.97,
  "pending_payment": -47.94,
  "num_people": 1,
  "reserved_time": null,
  "createdAt": null,
  "updatedAt": "2017-08-09T01:29:41.000Z",
  "rest": {
    "restaurant_id": 13,
    "name": "Red Hot Chilli",
    "phone": "3450693123",
    "operation_hours": "10am-3pm,5pm-10pm",
    "rating": 4.5,
    "street": "1125 San Carlos Ave",
    "apt": null,
    "city": "San Carlos",
    "state": "CA",
    "zip": "94070",
    "lat": 37.5068,
    "long": -122.26,
    "restaurant_url": "redhotchillipepperca.com",
    "cuisine": [
      "asian"
    ],
    "stripe_account": "acct_1ALjaPCstD5zm0ab",
    "image": null,
    "createdAt": "2017-07-02T05:51:00.000Z",
    "updatedAt": "2017-07-02T05:51:00.000Z",
    "email": "admie@foodbots.co"
  },
  "orders": [
    {
      "order": 30,
      "user": "1057808377646370",
      "item_id": {
        "item_id": 17,
        "name": "testitem",
        "price": 7.99,
        "description": null,
        "image": null,
        "category": "mexican",
        "createdAt": "2017-07-02T06:18:56.000Z",
        "updatedAt": "2017-07-02T06:18:56.000Z",
        "menu": 13
      },
      "rest_id": {
        "restaurant_id": 13,
        "name": "Red Hot Chilli",
        "phone": "3450693123",
        "operation_hours": "10am-3pm,5pm-10pm",
        "rating": 4.5,
        "street": "1125 San Carlos Ave",
        "apt": null,
        "city": "San Carlos",
        "state": "CA",
        "zip": "94070",
        "lat": 37.5068,
        "long": -122.26,
        "restaurant_url": "redhotchillipepperca.com",
        "cuisine": [
          "asian"
        ],
        "stripe_account": "acct_1ALjaPCstD5zm0ab",
        "image": null,
        "createdAt": "2017-07-02T05:51:00.000Z",
        "updatedAt": "2017-07-02T05:51:00.000Z",
        "email": "admie@foodbots.co"
      },
      "id": 106,
      "item_specifics": null,
      "quantity": 1,
      "item_total": 7.99,
      "status": "confirmed",
      "createdAt": "2017-07-16T08:54:54.000Z",
      "updatedAt": "2017-07-21T03:00:30.000Z"
    },
    {
      "order": 30,
      "user": "1043370582408888",
      "item_id": {
        "item_id": 17,
        "name": "testitem",
        "price": 7.99,
        "description": null,
        "image": null,
        "category": "mexican",
        "createdAt": "2017-07-02T06:18:56.000Z",
        "updatedAt": "2017-07-02T06:18:56.000Z",
        "menu": 13
      },
      "rest_id": {
        "restaurant_id": 13,
        "name": "Red Hot Chilli",
        "phone": "3450693123",
        "operation_hours": "10am-3pm,5pm-10pm",
        "rating": 4.5,
        "street": "1125 San Carlos Ave",
        "apt": null,
        "city": "San Carlos",
        "state": "CA",
        "zip": "94070",
        "lat": 37.5068,
        "long": -122.26,
        "restaurant_url": "redhotchillipepperca.com",
        "cuisine": [
          "asian"
        ],
        "stripe_account": "acct_1ALjaPCstD5zm0ab",
        "image": null,
        "createdAt": "2017-07-02T05:51:00.000Z",
        "updatedAt": "2017-07-02T05:51:00.000Z",
        "email": "admie@foodbots.co"
      },
      "id": 107,
      "item_specifics": null,
      "quantity": 2,
      "item_total": 15.98,
      "status": "confirmed",
      "createdAt": "2017-07-16T21:34:21.000Z",
      "updatedAt": "2017-07-21T03:06:55.000Z"
    }
  ]
}
